setup.py
Products/__init__.py
Products.EnhancedNewsItemImage.egg-info/PKG-INFO
Products.EnhancedNewsItemImage.egg-info/SOURCES.txt
Products.EnhancedNewsItemImage.egg-info/dependency_links.txt
Products.EnhancedNewsItemImage.egg-info/entry_points.txt
Products.EnhancedNewsItemImage.egg-info/namespace_packages.txt
Products.EnhancedNewsItemImage.egg-info/not-zip-safe
Products.EnhancedNewsItemImage.egg-info/requires.txt
Products.EnhancedNewsItemImage.egg-info/top_level.txt
Products/EnhancedNewsItemImage/__init__.py
Products/EnhancedNewsItemImage/changes.txt
Products/EnhancedNewsItemImage/readme.txt
Products/EnhancedNewsItemImage/_darcs/format
Products/EnhancedNewsItemImage/_darcs/hashed_inventory
Products/EnhancedNewsItemImage/_darcs/index_invalid
Products/EnhancedNewsItemImage/_darcs/tentative_pristine
Products/EnhancedNewsItemImage/_darcs/inventories/0000000186-6c56873ea6e591aa35abd4dc11b084ed8f295a134865c731cbcbb99939253b02
Products/EnhancedNewsItemImage/_darcs/inventories/0000000367-706e0088bbe5d9fa01b11fc52bddf762522d91ee33dd9513b8a1cc7eede556bf
Products/EnhancedNewsItemImage/_darcs/inventories/0000000566-d537576cb59e954877c73f9100b7c26a53fda5d0fba3a4da7cd61c0442fcafbc
Products/EnhancedNewsItemImage/_darcs/patches/0000000124-80cab447fea79847433ab1f28a7dfae5326651c82a30828e26384d6528bf1af8
Products/EnhancedNewsItemImage/_darcs/patches/0000000916-717a236fbb4c0a60d23a5a0f8f833748c9d38752f8904ea3165c96e9a074da17
Products/EnhancedNewsItemImage/_darcs/patches/0000001970-806aae9e0fdd8a24561c8d672585a9366f4a26d652347c8c45006571148c5544
Products/EnhancedNewsItemImage/_darcs/patches/pending
Products/EnhancedNewsItemImage/_darcs/patches/pending.tentative
Products/EnhancedNewsItemImage/_darcs/prefs/author
Products/EnhancedNewsItemImage/_darcs/prefs/binaries
Products/EnhancedNewsItemImage/_darcs/prefs/boring
Products/EnhancedNewsItemImage/_darcs/prefs/motd
Products/EnhancedNewsItemImage/_darcs/pristine.hashed/0000000000-e3b0c44298fc1c149afbf4c8996fb92427ae41e4649b934ca495991b7852b855
Products/EnhancedNewsItemImage/_darcs/pristine.hashed/0000000094-8452af1b52abe41efe019abb2d4533e854008a03e4df3d06a4170cb505f92dc4
Products/EnhancedNewsItemImage/_darcs/pristine.hashed/0000000094-c1d7e76b045151d67bbebed1bbd97634928dd8c7fd640d139af14b14209008c2
Products/EnhancedNewsItemImage/_darcs/pristine.hashed/0000000094-f6257e7cdd151e5ebbfb9a13a8b0bb83a4050c225d452fab3864406c0b9b623f
