Metadata-Version: 1.0
Name: Products.EnhancedNewsItemImage
Version: 1.0.3
Summary: Enhances regular news items so they can reference an image and makes image caption a requirement if image is set.
Home-page: http://www.nidelven-it.no/d
Author: Morten W. Petersen
Author-email: info@nidelven-it.no
License: GPL
Keywords: python plone atcontenttypes archetypes monkeypatch news accessibility
Platform: UNKNOWN
Classifier: Programming Language :: Python
Classifier: Framework :: Zope2
Classifier: Framework :: Plone
